[
  {
    "id": "jewish_001",
    "name": "Shema Yisrael",
    "english": "Hear, O Israel: the Lord is our God, the Lord is One",
    "original": "שְׁמַע יִשְׂרָאֵל יְהוָה אֱלֹהֵינוּ יְהוָה אֶחָד",
    "transliteration": "Shema Yisrael Adonai Eloheinu Adonai Echad",
    "abstract": "The Shema is the central declaration of Jewish faith, drawn from Deuteronomy 6:4, and is considered the most important prayer in Judaism. Its six Hebrew words proclaim the absolute unity of God — not merely that there is one God, but that the One is utterly without division or multiplicity. Recited twice daily, the Shema marks the Jewish understanding that existence is not fragmented but fundamentally whole at its source.\n\nThe Shema is traditionally recited with eyes closed and the right hand covering the eyes to prevent distraction, emphasizing that hearing — shema — means not merely acoustic reception but an inner listening with the full being. The word 'Echad' (One) is prolonged, allowing the practitioner to dwell in the space of that ultimate unity. Kabbalists say that in this prolongation, one briefly touches the world of Atzilut (Divine Emanation), the highest of the four worlds.\n\nThe Shema is also the dying declaration of Jewish martyrs throughout history — from Rabbi Akiva tortured by the Romans to those who perished in the Holocaust. Its use at death's threshold reflects the belief that the final act of consciousness should be an affirmation of divine unity. The Talmud relates that Rabbi Akiva expired on the word 'Echad,' teaching that a life of Torah reaches completion in this ultimate recognition.\n\nIn Kabbalistic practice, the Shema is understood as a unification ritual (yichud). Each word corresponds to a different dimension of divine reality: Yisrael points to the divine-human relationship, Adonai to the attribute of Judgment being unified with Elohim, and Echad to the integration of all worlds into their source. By reciting the Shema with this awareness, the practitioner participates in the cosmic work of tikkun — the repair and reunification of reality.\n\nContemporary Jewish meditation teachers have developed extended Shema practices where the six words are held in awareness for extended periods, with each word dissolving progressively into the next until only the recognition of pure unity remains. This approach treats the Shema not as a statement to be made but as a state to be entered — the state of perceiving all reality as expressions of one undivided being.",
    "tags": ["unity", "devotion", "focus", "wisdom", "prayer"],
    "tradition": "Jewish",
    "category": "Core Declaration",
    "difficulty": "beginner",
    "targetRepetitions": 3,
    "supportedLanguages": ["he", "en"],
    "translations": {
      "en": "Hear, O Israel: the Lord is our God, the Lord is One",
      "zh": "以色列啊，你要听：耶和华是我们的神，耶和华是唯一的",
      "es": "Escucha, Israel: el Señor es nuestro Dios, el Señor es Uno"
    },
    "audioUrl": null
  },
  {
    "id": "jewish_002",
    "name": "Ribbono Shel Olam",
    "english": "Master of the Universe",
    "original": "רִבּוֹנוֹ שֶׁל עוֹלָם",
    "transliteration": "Ribbono shel Olam",
    "abstract": "Ribbono shel Olam — Master of the Universe — is perhaps the most intimate divine address in Jewish prayer. While other divine names carry formal theological weight, this phrase is used in spontaneous, personal supplication, as if speaking directly to a sovereign who is also a friend. It appears throughout the Talmud in the mouths of the sages when making personal requests, and in Hasidic literature it has become the quintessential cry of the heart.\n\nThe Baal Shem Tov, founder of Hasidism, taught that the three words Ribbono shel Olam, uttered with simple sincerity, were sufficient to open the heavens. He emphasized that God does not require elaborate petition — the heart's plain, direct address is the most powerful prayer of all. His student Rebbe Nachman of Breslov built on this, developing the practice of hitbonenut — personal, informal, vernacular prayer — in which speaking to God as 'Ribbono shel Olam' in one's native language was actively encouraged.\n\nKabbalistically, the phrase encodes a complete cosmological statement. 'Ribbono' (Master) affirms divine sovereignty over all forces. 'Shel' (of) establishes relationship — God is not distant but has a specific connection to creation. 'Olam' (Universe) comes from the root 'alam' meaning 'hidden' — the universe is the dimension in which God's presence is concealed so that creation can have independent existence.\n\nIn Hasidic meditation, Ribbono shel Olam is used as an entry into deveikut — cleaving to God. The practice involves releasing all other thoughts and standing, as it were, in the direct awareness of divine presence, addressing God with these three words repeatedly until the separation between the self and its source diminishes.\n\nModern practitioners use Ribbono shel Olam as a reset phrase — a way of interrupting the momentum of habitual thought and reestablishing orientation. When life feels chaotic or meaningless, these three words place the practitioner back in relationship with the One who holds all of it. The simplicity is the point: in moments of crisis, elaborate language fails; the soul reaches for the most direct address it knows.",
    "tags": ["devotion", "surrender", "prayer", "trust", "connection"],
    "tradition": "Jewish",
    "category": "Hasidic Prayer",
    "difficulty": "beginner",
    "targetRepetitions": 10,
    "supportedLanguages": ["he", "en"],
    "translations": {
      "en": "Master of the Universe",
      "zh": "宇宙的主宰",
      "es": "Señor del Universo"
    },
    "audioUrl": null
  },
  {
    "id": "jewish_003",
    "name": "Baruch Atah Adonai",
    "english": "Blessed are You, O Lord our God",
    "original": "בָּרוּךְ אַתָּה יְהוָה אֱלֹהֵינוּ",
    "transliteration": "Baruch Atah Adonai Eloheinu",
    "abstract": "Baruch Atah Adonai Eloheinu is the opening formula of nearly every Jewish blessing (bracha), occurring over 100 times in the traditional Jewish prayer book (siddur). It is the entry gate into blessing-consciousness — the recognition that ordinary moments of life (eating bread, lighting candles, seeing a rainbow, hearing good news) are occasions for acknowledging divine presence. Through the bracha formula, the mundane and the sacred are consciously unified.\n\nThe word 'baruch' (blessed) is grammatically unusual — it is a passive-form adjective applied to God, raising the question of how humans can 'bless' God who is the source of all blessing. The Talmudic response is that human blessing flows back to its divine source as gratitude and recognition; we do not add to God's reality but we acknowledge it, and in that acknowledgment, divine presence is more fully present in the world.\n\nThe particular power of the bracha structure lies in its shift of pronouns: 'Baruch Atah' — Blessed are You (second person) — shifts in the next clause to 'Asher kidshanu' — Who has sanctified us (third person). This movement from 'You' to 'Who' mirrors the mystic's experience of approaching divine presence: intimate address suddenly opens into an ineffable vastness that can only be spoken of in the third person.\n\nIn contemplative Jewish practice, the discipline of reciting 100 brachot per day is understood as a training of perception: to see 100 moments per day as occasions for gratitude transforms consciousness fundamentally. Each blessing requires a moment of pause, a shift from taking for granted to actively noticing and responding. Over time, this practice develops what Rabbi Abraham Joshua Heschel called 'radical amazement.'\n\nKabbalists associate the bracha formula with specific sephirot (divine emanations). 'Baruch' corresponds to Keter (Crown), the highest and most hidden; 'Atah' to Chokhmah (Wisdom) and Binah (Understanding); 'Adonai' to Malkhut (Kingdom). The bracha is thus a full traversal of the divine tree, from the hidden source to its manifestation in the world.",
    "tags": ["gratitude", "prayer", "devotion", "mindfulness", "sacred"],
    "tradition": "Jewish",
    "category": "Bracha / Blessing Formula",
    "difficulty": "beginner",
    "targetRepetitions": 100,
    "supportedLanguages": ["he", "en"],
    "translations": {
      "en": "Blessed are You, O Lord our God",
      "zh": "有福的是祢，我们的主我们的神",
      "es": "Bendito seas Tú, Señor nuestro Dios"
    },
    "audioUrl": null
  },
  {
    "id": "jewish_004",
    "name": "Echad",
    "english": "One",
    "original": "אֶחָד",
    "transliteration": "Echad",
    "abstract": "Echad — One — is the final and most weighted word of the Shema, prolonged in traditional prayer while the practitioner holds in awareness the unity of the divine and the unity of all existence. It is simultaneously the simplest and most profound word in the Jewish liturgical vocabulary, condensing the entirety of Jewish theology into a single syllable: the absolute non-duality of reality at its source.\n\nThe three letters of Echad — Aleph, Chet, Dalet — are given Kabbalistic significance. The Aleph (1) represents the divine unity; the Chet (8) represents the seven directions of space plus their transcendent source; and the Dalet (4) represents the four cardinal directions of the earthly realm. Together they encode the divine One permeating all dimensions of space-time.\n\nIn the Nusach Sefard tradition, the word Echad is held for the count of ten — representing the ten sephirot of Kabbalah — while the practitioner meditates on God's dominion extending through all levels of reality. This brief meditation within the Shema is considered by many masters the most concentrated moment of Jewish prayer, a point at which normal consciousness is temporarily suspended.\n\nRebbe Nachman of Breslov taught a meditation on Echad for practitioners struggling with confusion or fragmentation. By simply repeating this one word slowly, feeling its meaning rather than thinking about it, the mind begins to release its habitual division of experience into problems, conflicts, and distinctions. The single word acts as a solvent of multiplicity.\n\nIn contemporary Jewish mindfulness, Echad is used as a single-word mantra during sitting meditation. Unlike longer formulas that engage the thinking mind, the single word Echad is brief enough to be held in pure awareness. As it is repeated slowly, the gap between repetitions expands, and in those gaps, practitioners report touching the silence that is the experiential correlate of divine unity.",
    "tags": ["unity", "focus", "liberation", "meditation", "wisdom"],
    "tradition": "Jewish",
    "category": "Kabbalistic Meditation",
    "difficulty": "intermediate",
    "targetRepetitions": 26,
    "supportedLanguages": ["he", "en"],
    "translations": {
      "en": "One",
      "zh": "一",
      "es": "Uno"
    },
    "audioUrl": null
  },
  {
    "id": "jewish_005",
    "name": "Ana B'Koach",
    "english": "Please, with the strength of Your right hand, untie the bundled sins",
    "original": "אָנָּא בְּכֹחַ גְּדֻלַּת יְמִינְךָ תַּתִּיר צְרוּרָה",
    "transliteration": "Ana B'koach gedullat yemincha tatir tzerurah",
    "abstract": "Ana B'Koach is a mystical prayer composed of 42 words in seven lines, attributed by tradition to the first-century sage Rabbi Nechunia ben HaKanah. Each of the 42 words begins with a letter that, when combined, forms one of the 72 Names of God — the 42-letter divine name (Shem Mem-Bet). This hidden name is considered by Kabbalists to be among the most powerful of all sacred formulas, encoding the mechanism of creation itself.\n\nThe forty-two letter name embedded in Ana B'Koach corresponds to the 42 journeys of the Israelites through the desert, which Kabbalists interpret as a map of the soul's journey through different levels of consciousness. Each journey represents a stage of spiritual refinement, and the complete prayer is a recapitulation of the entire spiritual path, from Egypt (the narrowness of ego-consciousness) to the Promised Land (expanded divine awareness).\n\nIn Kabbalah, Ana B'Koach is placed at the transition between Friday afternoon and Shabbat, recited as one crosses the threshold from the six days of labor into the sacred seventh day. The 42-letter name is associated with the creative force of the six days of creation, and the prayer invokes that creative power while asking for the release of what is 'bundled' (tzerurah) — the accumulated spiritual heaviness of the week.\n\nThe prayer is recited both aloud and in silent contemplation. The Ari (Rabbi Isaac Luria) prescribed reciting Ana B'Koach while meditating on the specific combinations of letters in each line, with each letter activating a different divine quality. His student Chayyim Vital described this practice as direct manipulation of the spiritual structures underlying physical reality.\n\nModern practitioners use Ana B'Koach as a forgiveness and release prayer. Each line asks for specific spiritual assistance: liberation from constriction, blessing, exaltation, purity, and divine protection. Reciting it slowly at the end of the week or at significant transitions, practitioners report a sense of spiritual clearing — as if the prayer gathers and dissolves accumulated psychic weight, leaving the soul lighter and more spacious.",
    "tags": ["cleansing", "liberation", "healing", "protection", "transformation"],
    "tradition": "Jewish",
    "category": "Kabbalistic Prayer",
    "difficulty": "advanced",
    "targetRepetitions": 7,
    "supportedLanguages": ["he", "en"],
    "translations": {
      "en": "Please, with the strength of Your right hand, untie the bundled sins",
      "zh": "请凭借祢右手力量之伟大，解开那捆绑的罪",
      "es": "Por favor, con la fuerza de Tu mano derecha, desata los pecados anudados"
    },
    "audioUrl": null
  },
  {
    "id": "jewish_006",
    "name": "Modeh Ani",
    "english": "I offer thanks before You, living and eternal King",
    "original": "מוֹדֶה אֲנִי לְפָנֶיךָ מֶלֶךְ חַי וְקַיָּם",
    "transliteration": "Modeh ani lefanecha melech chai ve'kayyam",
    "abstract": "Modeh Ani is the first prayer of the Jewish day, recited immediately upon waking before even rising from bed — before washing hands, before the morning blessings, before any other act. Its form deliberately places 'Modeh' (I am grateful) before 'Ani' (I), because before asserting one's existence, one acknowledges the source of that existence. The day begins not with 'I' but with gratitude.\n\nThe prayer thanks God for returning the soul to the body after the sleep that Jewish tradition calls 'one-sixtieth of death.' Each morning is understood as a micro-resurrection — the soul is received by divine hands during sleep and returned at waking with renewed potential. Modeh Ani acknowledges this gift and orients the waking consciousness immediately toward gratitude as the primary stance toward existence.\n\nNotably, Modeh Ani contains no divine name, making it the rare prayer that can be recited even in a state of ritual impurity (before morning washing). The rabbis designed it this way deliberately: the first act of consciousness every day should be gratitude, without any ritual prerequisite. Gratitude requires nothing but awareness and a willing heart.\n\nHasidic masters use Modeh Ani as an entry into 'the point of truth' — the moment before the habitual self reconstructs itself after sleep. For a brief window upon waking, the accumulated narratives of identity, grievance, and anxiety have not yet reassembled. Modeh Ani catches this window and fills it with gratitude and awe, establishing the day's foundational tone before the ego has a chance to impose its agenda.\n\nContemporary practitioners of Jewish mindfulness extend the Modeh Ani into a brief morning body scan and gratitude practice. After reciting the traditional lines, they spend a few minutes noticing what functions in the body — breath, heartbeat, senses — and mentally offering each as an occasion for gratitude. Research in positive psychology validates this ancient practice: daily gratitude exercises first thing in the morning demonstrably shift baseline mood and increase resilience.",
    "tags": ["gratitude", "beginnings", "mindfulness", "devotion", "peace"],
    "tradition": "Jewish",
    "category": "Morning Prayer",
    "difficulty": "beginner",
    "targetRepetitions": 1,
    "supportedLanguages": ["he", "en"],
    "translations": {
      "en": "I offer thanks before You, living and eternal King",
      "zh": "我感谢祢，永活永存的君王",
      "es": "Te doy gracias ante Ti, Rey eterno y viviente"
    },
    "audioUrl": null
  },
  {
    "id": "jewish_007",
    "name": "Shalom",
    "english": "Peace, Wholeness, and Complete Well-being",
    "original": "שָׁלוֹם",
    "transliteration": "Shalom",
    "abstract": "Shalom is among the most widely known Hebrew words in the world — the universal Jewish greeting and farewell, a word that means simultaneously peace, wholeness, completeness, and well-being. Its root, shalem, connects to health, integrity, and the absence of deficiency. Shalom is therefore not merely the cessation of conflict but a positive state of harmony in which every part is in its proper relationship to the whole.\n\nIn Kabbalistic tradition, Shalom is one of the names of God — HaShalom, the One who is Peace. This identification is profound: God is not described as the giver of peace but as Peace itself. Just as God is the source of all light, life, and being, so too is God the source of all shalom. Human experience of peace is therefore a direct contact with the divine nature.\n\nThe Mishnah concludes with a teaching that the only vessel that holds blessing is peace. This is interpreted to mean that all other spiritual attainments — wisdom, piety, scholarship, charity — can only be received and retained in a vessel of inner peace. Without shalom, the capacity to contain blessing is absent, no matter how worthy the person.\n\nIn contemplative practice, the Hebrew greeting 'Shalom Aleichem' (Peace be upon you) is used as a mantra of blessing. Practitioners extend the phrase silently toward everyone they encounter throughout the day, including people they find difficult, people suffering, and even themselves. This practice trains compassionate awareness and gradually dissolves the habitual division between self and other.\n\nThe angels' song 'Shalom Aleichem' sung on Friday evening to welcome the Shabbat angels also functions as a mantra. Its repetitive structure, sung to traditional melodies, induces a gentle trance state associated with the transition into Shabbat consciousness — what Jewish tradition describes as a 'foretaste of the world to come,' where the quality of shalom prevails without interruption.",
    "tags": ["peace", "healing", "unity", "connection", "blessing"],
    "tradition": "Jewish",
    "category": "Sacred Greeting / Divine Name",
    "difficulty": "beginner",
    "targetRepetitions": 36,
    "supportedLanguages": ["he", "en"],
    "translations": {
      "en": "Peace, Wholeness, and Complete Well-being",
      "zh": "平安、完整与全然的安康",
      "es": "Paz, plenitud y bienestar completo"
    },
    "audioUrl": null
  },
  {
    "id": "jewish_008",
    "name": "Ein Sof",
    "english": "The Infinite — Without End",
    "original": "אֵין סוֹף",
    "transliteration": "Ein Sof",
    "abstract": "Ein Sof — Without End, The Infinite — is the Kabbalistic term for the ultimate divine reality beyond all names, attributes, and descriptions. In the Zohar and subsequent Kabbalistic literature, Ein Sof is the absolute ground of being, so utterly beyond conception that not even the divine names of the Torah can be applied to it literally. It is from Ein Sof that all the divine emanations (sephirot) emerge, and toward Ein Sof that all existence ultimately tends.\n\nThe term first appears systematically in the writings of Rabbi Azriel of Gerona in the thirteenth century. Its emergence represents a turning point in Jewish theology: by insisting that God's ultimate nature is beyond all positive description — beyond wisdom, beyond love, beyond even being in any sense we understand — the Kabbalists preserved the genuine ineffability of the divine while still mapping the terrain of divine emanation.\n\nMeditating on Ein Sof is an advanced practice in the Kabbalah. Unlike mantras that invoke specific divine qualities, contemplating Ein Sof requires the meditator to voluntarily dissolve all conceptual handles. One moves through the sephirot (divine attributes) as stepping stones, releasing each in turn, until one approaches the awareness of pure, boundless, attribute-free existence. This practice is analogous to apophatic theology in Christian mysticism and nirguna meditation in Advaita Vedanta.\n\nRabbi Moshe Cordovero in his Pardes Rimonim describes Ein Sof as the light that illuminates all the divine vessels from within. The sephirot are not separate from Ein Sof but are the way Ein Sof makes itself accessible to finite consciousness — like a spectrum of colors that is still, at its source, pure white light. To meditate on Ein Sof is to trace those colors back to their undivided source.\n\nIn contemporary Neo-Hasidic practice, Ein Sof is approached through the experience of natural awe — standing before the ocean, gazing at a starfield, or sitting in old-growth forest and feeling one's own smallness in the face of the vast. This somatic encounter with the unbounded is understood as a direct meeting with Ein Sof, as the boundary of individual identity temporarily becomes permeable to the infinite.",
    "tags": ["unity", "mystery", "liberation", "wisdom", "awe"],
    "tradition": "Jewish",
    "category": "Kabbalistic Concept / Meditation",
    "difficulty": "advanced",
    "targetRepetitions": 10,
    "supportedLanguages": ["he", "en"],
    "translations": {
      "en": "The Infinite — Without End",
      "zh": "无限——无终无止",
      "es": "Lo Infinito — Sin Fin"
    },
    "audioUrl": null
  },
  {
    "id": "jewish_009",
    "name": "Hineni",
    "english": "Here I Am — complete, present, ready",
    "original": "הִנֵּנִי",
    "transliteration": "Hineni",
    "abstract": "Hineni — Here I Am — is the single most recurring response to divine call in the Hebrew Bible. Abraham says Hineni when God calls him to sacrifice Isaac. Moses says Hineni at the burning bush. Samuel says Hineni when he hears his name called in the night. Isaiah says Hineni when God asks 'Whom shall I send?' The word appears at every defining moment of divine-human encounter, representing the foundational human response to transcendence: full presence, availability, readiness.\n\nThe word is deceptively simple: it is the word 'here' (hen) plus the first-person suffix 'ni' (me). 'I am here.' Yet in its biblical contexts it carries enormous weight. To say Hineni is not merely to report one's physical location; it is to offer one's entire being — to stand undivided, without reservation, in the face of whatever the moment requires. It is the anti-distraction, the total mobilization of self in response to a call.\n\nIn Hasidic thought, Hineni is the stance that God asks of human beings in every moment, not only in dramatic divine encounters. Every instant presents a call — the need of another person, the opportunity for a kind act, the voice of conscience — and the spiritual life consists of being present enough to hear and respond with Hineni. The masters teach that most human suffering comes from not being present — from living in memory or anticipation rather than here, in this moment.\n\nContemplative use of Hineni involves sitting quietly and, on each breath, offering it as a Hineni — a gift of presence. The inhale is the call; the exhale is the response. Gradually the boundaries between the one who is present and the presence itself soften. Practitioners find that consistent Hineni practice develops what Jewish teachers call kavanah (directed intention), the quality of full engagement that distinguishes routine from sacred action.\n\nRabbi Abraham Joshua Heschel wrote that wonder is the beginning of spiritual life and that what we need is not more information but more presence. Hineni encodes this teaching: before wisdom, before knowledge, before any spiritual attainment, one must simply be here. The word is a practice of arriving — again and again, breath by breath — in the only place where God and life can actually be encountered: the present moment.",
    "tags": ["presence", "devotion", "courage", "transformation", "surrender"],
    "tradition": "Jewish",
    "category": "Biblical Invocation",
    "difficulty": "beginner",
    "targetRepetitions": 18,
    "supportedLanguages": ["he", "en"],
    "translations": {
      "en": "Here I Am — complete, present, ready",
      "zh": "我在这里——完全、当下、准备好了",
      "es": "Aquí estoy — completo, presente, listo"
    },
    "audioUrl": null
  },
  {
    "id": "jewish_010",
    "name": "Elohim",
    "english": "God — the Power of Powers, the plural unity of divine forces",
    "original": "אֱלֹהִים",
    "transliteration": "Elohim",
    "abstract": "Elohim is one of the primary Hebrew divine names appearing throughout the Hebrew Bible, most famously as the name used in the first chapter of Genesis: 'In the beginning Elohim created the heavens and the earth.' Grammatically plural but theologically singular, Elohim encodes within its form the mystery of divine unity expressing itself through infinite multiplicity — the One that contains and manifests as the many.\n\nThe numerical value (gematria) of Elohim is 86, identical to the value of HaTeva (Nature). This equivalence, noted by Kabbalists from the Baal Shem Tov onward, suggests that Nature and the divine name Elohim are the same reality perceived from different levels of awareness. Those who see only natural processes see HaTeva; those who perceive the divine intelligence within those same processes see Elohim.\n\nIn the sephirotic system, Elohim is the name associated with the sephira of Binah (Understanding) — the divine mother, the womb of creation, the formative intelligence that shapes the infinite flow of divine light into the specific forms of existence. Reciting or meditating on Elohim is an invocation of this formative, nurturing, structuring aspect of divine intelligence.\n\nThe plural form of Elohim has invited theological reflection throughout Jewish history. While mainstream Judaism reads it as a 'plural of majesty,' Kabbalists read the plurality as pointing to the divine attribute-forces (sephirot) that are multiple in their manifestation but one in their source. Every divine quality — wisdom, understanding, love, judgment, beauty — is an Eloah (singular), and Elohim is their unity.\n\nMeditation on Elohim involves holding in awareness the paradox of one and many, unity and diversity. Practitioners are invited to notice the same dynamic in their own experience: there are many thoughts, emotions, sensations — and yet they all arise in a single awareness. That awareness is the experiential correlate of Elohim — the one field in which all the many arise.",
    "tags": ["unity", "wisdom", "awe", "mystery", "creation"],
    "tradition": "Jewish",
    "category": "Divine Name",
    "difficulty": "intermediate",
    "targetRepetitions": 26,
    "supportedLanguages": ["he", "en"],
    "translations": {
      "en": "God — the Power of Powers, the plural unity of divine forces",
      "zh": "神——诸力之力，神圣力量的多元一体",
      "es": "Dios — el Poder de Poderes, la unidad plural de fuerzas divinas"
    },
    "audioUrl": null
  },
  {
    "id": "jewish_011",
    "name": "L'Chaim",
    "english": "To Life!",
    "original": "לְחַיִּים",
    "transliteration": "L'chaim",
    "abstract": "L'Chaim — To Life! — is the universal Jewish toast and an affirmation that has far exceeded its role as a drinking gesture to become a complete spiritual stance. To say L'Chaim is to align oneself with the force of life itself — to choose vitality, engagement, and the affirmation of existence over withdrawal, resignation, or despair. In a tradition where the preservation of life (pikuach nefesh) overrides virtually all other commandments, L'Chaim is both theology and daily practice.\n\nHasidic masters teach that the divine name Chayyim (Life) is one of the most direct names of God because God is not merely alive but is the very principle of life itself — 'the living God' (Elohim Chayyim). To say L'Chaim is therefore to invoke and affirm divine presence: every instance of life, in any creature, is a flame from the fire of divine vitality. The toast is an act of recognizing the sacred in the biological.\n\nIn times of grief and loss — which have been frequent in Jewish history — L'Chaim takes on deeper resonance. To say L'Chaim at a shiva (mourning house), as Jewish tradition encourages, is an act of radical affirmation in the face of death. It says: even in this darkness, we choose life. Even now, we assert that the force of existence is stronger than the fact of death. This is not denial but a fierce, deliberate orientation of the soul toward the source of being.\n\nAs a daily mantra, L'Chaim can be whispered as a greeting to each new moment — each breath, each sunrise, each encounter. It transforms the repetitive into the revelatory. Teachers in the Jewish Renewal movement, particularly Rabbi Zalman Schachter-Shalomi, used L'Chaim as a practice of 'enlivening' — bringing full presence to whatever one is doing.\n\nThe phrase appears in its full form across Jewish liturgy and folk tradition. Its endurance across centuries and vastly different cultural contexts — from the shtetls of Eastern Europe to modern Israel to Jewish communities worldwide — testifies to the deep human need for an affirmation of life that is simple, joyful, and unconditional.",
    "tags": ["vitality", "joy", "gratitude", "presence", "blessing"],
    "tradition": "Jewish",
    "category": "Sacred Affirmation",
    "difficulty": "beginner",
    "targetRepetitions": 18,
    "supportedLanguages": ["he", "en"],
    "translations": {
      "en": "To Life!",
      "zh": "为了生命！",
      "es": "¡Por la vida!"
    },
    "audioUrl": null
  },
  {
    "id": "jewish_012",
    "name": "Tikkun Olam",
    "english": "Repair of the World",
    "original": "תִּיקּוּן עוֹלָם",
    "transliteration": "Tikkun Olam",
    "abstract": "Tikkun Olam — Repair of the World — originates in Kabbalistic cosmology as a technical term for the spiritual work of restoring divine sparks (nitzotzot) to their source. According to the Lurianic Kabbalah of Rabbi Isaac Luria, the vessels (kelim) meant to contain divine light shattered at creation (shevirat ha-kelim), scattering sparks of divine light throughout the material world. The purpose of human existence and spiritual practice is to gather these sparks through conscious action and return them to the divine source.\n\nIn Lurianic theology, every mitzvah (divine commandment), every act of kindness, every moment of authentic prayer, every ethical choice — these all 'raise the sparks' embedded in the materials and situations involved. Eating with awareness, conducting business with integrity, speaking truth, loving one's neighbor — all are forms of Tikkun. The entire social-ethical program of Judaism is framed as cosmic repair work, giving every human act ultimate metaphysical significance.\n\nThe phrase entered mainstream discourse through the Reform and Reconstructionist movements of the twentieth century, where it came to denote social justice work more broadly. Tikkun Olam in this usage means any effort to alleviate suffering, reduce inequality, protect the environment, or advance human dignity. The ethical imperative it expresses is genuinely continuous with the tradition's deepest values.\n\nAs a mantra, Tikkun Olam serves as an intention-setter. Before engaging in any activity — work, parenting, creative endeavor, social action — pausing to whisper Tikkun Olam frames that activity as part of the cosmic repair project. It transforms the mundane into the purposeful, connecting individual action to the largest possible frame of meaning. This reframing is a powerful antidote to nihilism and the sense that one's actions are too small to matter.\n\nContemporary practitioners of Jewish mindfulness use Tikkun Olam in combination with breath awareness: with each inhale, one draws in the brokenness of the world; with each exhale, one releases healing intention. This is a practice not of toxic positivity but of engaged compassion — the willingness to be present to what is broken in oneself and in the world, and to offer whatever capacity for healing one has, without demanding results.",
    "tags": ["wisdom", "compassion", "service", "transformation", "purpose"],
    "tradition": "Jewish",
    "category": "Kabbalistic Intention",
    "difficulty": "intermediate",
    "targetRepetitions": 10,
    "supportedLanguages": ["he", "en"],
    "translations": {
      "en": "Repair of the World",
      "zh": "修复世界",
      "es": "Reparación del Mundo"
    },
    "audioUrl": null
  }
]
